dave_data/__init__.py
dave_data/__main__.py
dave_data/cli.py
dave_data/core.py
dave_data/datapool/__init__.py
dave_data/datapool/osm_request.py
dave_data-0.0.1.dist-info/AUTHORS.rst
dave_data-0.0.1.dist-info/LICENSE
dave_data-0.0.1.dist-info/METADATA
dave_data-0.0.1.dist-info/WHEEL
dave_data-0.0.1.dist-info/entry_points.txt
dave_data-0.0.1.dist-info/top_level.txt
dave_data-0.0.1.dist-info/RECORD
