Metadata-Version: 2.1
Name: dave_data
Version: 0.0.1
Summary: Short Discription
Home-page: https://github.com/DaveFoss/DAVE_data
Author: DAVE_data Developers
Author-email: EMAIL@IS.MISSING.DE
License: MIT
Project-URL: Documentation, https://dave_data.readthedocs.io
Project-URL: Changelog, https://dave_data.readthedocs.ioen/latest/changelog.html
Project-URL: Issue Tracker, https://github.com/DaveFoss/DAVE_data/issues
Classifier: Development Status :: 5 - Production/Stable
Classifier: Intended Audience :: Developers
Classifier: License :: OSI Approved :: MIT License
Classifier: Operating System :: Unix
Classifier: Operating System :: POSIX
Classifier: Operating System :: Microsoft :: Windows
Classifier: Programming Language :: Python
Classifier: Programming Language :: Python :: 3
Classifier: Programming Language :: Python :: 3 :: Only
Classifier: Programming Language :: Python :: 3.10
Classifier: Programming Language :: Python :: 3.11
Classifier: Programming Language :: Python :: 3.12
Classifier: Programming Language :: Python :: Implementation :: CPython
Classifier: Programming Language :: Python :: Implementation :: PyPy
Classifier: Topic :: Utilities
Requires-Python: >=3.8
License-File: LICENSE
License-File: AUTHORS.rst
Requires-Dist: pandas
Requires-Dist: geopandas
Requires-Dist: defusedxml
Requires-Dist: six
Provides-Extra: examples
Requires-Dist: contextily; extra == "examples"
Requires-Dist: shapely; extra == "examples"
Requires-Dist: matplotlib; extra == "examples"
